{
  "$schema": "https://developer.microsoft.com/json-schemas/fabric/item/report/definition/visualContainer/1.5.0/schema.json",
  "name": "3f942e0499d4404e339e",
  "position": {
    "x": 848.00000000000011,
    "y": 400.00000000000006,
    "z": 6000,
    "height": 288,
    "width": 400.00000000000006,
    "tabOrder": 5000
  },
  "visual": {
    "visualType": "lineChart",
    "query": {
      "queryState": {
        "Category": {
          "projections": [
            {
              "field": {
                "HierarchyLevel": {
                  "Expression": {
                    "Hierarchy": {
                      "Expression": {
                        "SourceRef": {
                          "Entity": "Dates"
                        }
                      },
                      "Hierarchy": "Financial Date Hierarchy"
                    }
                  },
                  "Level": "Week"
                }
              },
              "queryRef": "Dates.Financial Date Hierarchy.Week",
              "nativeQueryRef": "Financial Date Hierarchy Week",
              "active": true
            }
          ]
        },
        "Series": {
          "projections": [
            {
              "field": {
                "HierarchyLevel": {
                  "Expression": {
                    "Hierarchy": {
                      "Expression": {
                        "SourceRef": {
                          "Entity": "Dates"
                        }
                      },
                      "Hierarchy": "Financial Date Hierarchy"
                    }
                  },
                  "Level": "Year"
                }
              },
              "queryRef": "Dates.Financial Date Hierarchy.Year",
              "nativeQueryRef": "Financial Date Hierarchy Year"
            }
          ]
        },
        "Y": {
          "projections": [
            {
              "field": {
                "Measure": {
                  "Expression": {
                    "SourceRef": {
                      "Entity": "Order Measures"
                    }
                  },
                  "Property": "Order Value Gross Ex Vat"
                }
              },
              "queryRef": "Order Measures.Order Value Gross Ex Vat",
              "nativeQueryRef": "Order Value Gross Ex Vat",
              "hidden": true
            },
            {
              "field": {
                "NativeVisualCalculation": {
                  "Language": "dax",
                  "Expression": "RUNNINGSUM([Order Value Gross Ex Vat])",
                  "Name": "Running Order Value Gross Ex Vat"
                }
              },
              "queryRef": "select",
              "nativeQueryRef": "Running Order Value Gross Ex Vat"
            }
          ]
        }
      }
    },
    "objects": {
      "zoom": [
        {
          "properties": {
            "show": {
              "expr": {
                "Literal": {
                  "Value": "false"
                }
              }
            },
            "showOnValueAxis": {
              "expr": {
                "Literal": {
                  "Value": "false"
                }
              }
            }
          }
        }
      ]
    },
    "visualContainerObjects": {
      "title": [
        {
          "properties": {
            "text": {
              "expr": {
                "Literal": {
                  "Value": "'Running Sum of Order Value for Add-ons'"
                }
              }
            }
          }
        }
      ]
    },
    "drillFilterOtherVisuals": true
  }
}
