{
  "$schema": "https://developer.microsoft.com/json-schemas/fabric/item/report/definition/visualContainer/1.5.0/schema.json",
  "name": "32ef5d275810d651a5b0",
  "position": {
    "x": 32,
    "y": 96,
    "z": 2000,
    "height": 288,
    "width": 1216,
    "tabOrder": 2000
  },
  "visual": {
    "visualType": "lineStackedColumnComboChart",
    "query": {
      "queryState": {
        "Category": {
          "projections": [
            {
              "field": {
                "HierarchyLevel": {
                  "Expression": {
                    "Hierarchy": {
                      "Expression": {
                        "SourceRef": {
                          "Entity": "Dates"
                        }
                      },
                      "Hierarchy": "Financial Date Hierarchy"
                    }
                  },
                  "Level": "Year"
                }
              },
              "queryRef": "Dates.Financial Date Hierarchy.Year",
              "nativeQueryRef": "Financial Date Hierarchy Year",
              "active": true
            },
            {
              "field": {
                "HierarchyLevel": {
                  "Expression": {
                    "Hierarchy": {
                      "Expression": {
                        "SourceRef": {
                          "Entity": "Dates"
                        }
                      },
                      "Hierarchy": "Financial Date Hierarchy"
                    }
                  },
                  "Level": "Quarter"
                }
              },
              "queryRef": "Dates.Financial Date Hierarchy.Quarter",
              "nativeQueryRef": "Financial Date Hierarchy Quarter",
              "active": true
            },
            {
              "field": {
                "HierarchyLevel": {
                  "Expression": {
                    "Hierarchy": {
                      "Expression": {
                        "SourceRef": {
                          "Entity": "Dates"
                        }
                      },
                      "Hierarchy": "Financial Date Hierarchy"
                    }
                  },
                  "Level": "Week"
                }
              },
              "queryRef": "Dates.Financial Date Hierarchy.Week",
              "nativeQueryRef": "Financial Date Hierarchy Week",
              "active": true
            }
          ]
        },
        "Series": {
          "projections": [
            {
              "field": {
                "Column": {
                  "Expression": {
                    "SourceRef": {
                      "Entity": "Billing Agreements"
                    }
                  },
                  "Property": "Payment Method"
                }
              },
              "queryRef": "Billing Agreements.Payment Method",
              "nativeQueryRef": "Payment Method"
            }
          ]
        },
        "Y": {
          "projections": [
            {
              "field": {
                "Measure": {
                  "Expression": {
                    "SourceRef": {
                      "Entity": "Order Measures"
                    }
                  },
                  "Property": "Number of Orders"
                }
              },
              "queryRef": "Order Measures.Number of Orders",
              "nativeQueryRef": "Number of Orders"
            }
          ]
        }
      }
    },
    "visualContainerObjects": {
      "title": [
        {
          "properties": {
            "text": {
              "expr": {
                "Literal": {
                  "Value": "'Number of Orders'"
                }
              }
            }
          }
        }
      ]
    },
    "drillFilterOtherVisuals": true
  }
}
