{
  "$schema": "https://developer.microsoft.com/json-schemas/fabric/item/report/definition/page/2.0.0/schema.json",
  "name": "7bfcc194062d305c2aea",
  "displayName": "Duplicate of Case cost (Ex VAT) *NEED OTHER MEASURES",
  "displayOption": "FitToPage",
  "height": 720,
  "width": 1280,
  "pageBinding": {
    "name": "c99dd5a5a1113ee9d0d5",
    "type": "Default",
    "parameters": []
  },
  "objects": {
    "background": [
      {
        "properties": {
          "image": {
            "image": {
              "name": {
                "expr": {
                  "Literal": {
                    "Value": "'Cheffelo-Report-Background.svg'"
                  }
                }
              },
              "url": {
                "expr": {
                  "ResourcePackageItem": {
                    "PackageName": "RegisteredResources",
                    "PackageType": 1,
                    "ItemName": "Cheffelo-Report-Background2417383144405547.svg"
                  }
                }
              },
              "scaling": {
                "expr": {
                  "Literal": {
                    "Value": "'Fit'"
                  }
                }
              }
            }
          }
        }
      }
    ]
  },
  "visibility": "HiddenInViewMode"
}