{
  "$schema": "https://developer.microsoft.com/json-schemas/fabric/item/report/definition/visualContainer/1.2.0/schema.json",
  "name": "d3c8194bcb22ed253cc7",
  "position": {
    "x": 0,
    "y": 395.35985679437005,
    "z": 1000,
    "height": 324.91391867464591,
    "width": 1263.713869535459
  },
  "visual": {
    "visualType": "columnChart",
    "query": {
      "queryState": {
        "Category": {
          "projections": [
            {
              "field": {
                "Column": {
                  "Expression": {
                    "SourceRef": {
                      "Entity": "Recipes"
                    }
                  },
                  "Property": "Recipe Main Ingredient Name"
                }
              },
              "queryRef": "Recipes.Recipe Main Ingredient Name",
              "nativeQueryRef": "Recipe Main Ingredient Name",
              "active": true
            }
          ]
        },
        "Series": {
          "projections": [
            {
              "field": {
                "Column": {
                  "Expression": {
                    "SourceRef": {
                      "Entity": "Billing Agreements"
                    }
                  },
                  "Property": "Is OneSub"
                }
              },
              "queryRef": "Billing Agreements.Is OneSub",
              "nativeQueryRef": "Is OneSub"
            }
          ]
        },
        "Y": {
          "projections": [
            {
              "field": {
                "Measure": {
                  "Expression": {
                    "SourceRef": {
                      "Entity": "Order Measures"
                    }
                  },
                  "Property": "Diff Added vs Removed Dishes"
                }
              },
              "queryRef": "Order Measures.Diff Added vs Removed Dishes",
              "nativeQueryRef": "Diff Added vs Removed Dishes"
            }
          ]
        }
      },
      "sortDefinition": {
        "sort": [
          {
            "field": {
              "Measure": {
                "Expression": {
                  "SourceRef": {
                    "Entity": "Order Measures"
                  }
                },
                "Property": "Diff Added vs Removed Dishes"
              }
            },
            "direction": "Descending"
          }
        ],
        "isDefaultSort": true
      }
    },
    "objects": {
      "dataPoint": [
        {
          "properties": {
            "fill": {
              "solid": {
                "color": {
                  "expr": {
                    "Conditional": {
                      "Cases": [
                        {
                          "Condition": {
                            "Comparison": {
                              "ComparisonKind": 3,
                              "Left": {
                                "Measure": {
                                  "Expression": {
                                    "SourceRef": {
                                      "Entity": "Order Measures"
                                    }
                                  },
                                  "Property": "Diff Added vs Removed Dishes"
                                }
                              },
                              "Right": {
                                "Literal": {
                                  "Value": "0D"
                                }
                              }
                            }
                          },
                          "Value": {
                            "Literal": {
                              "Value": "'#E66C37'"
                            }
                          }
                        },
                        {
                          "Condition": {
                            "Comparison": {
                              "ComparisonKind": 2,
                              "Left": {
                                "Measure": {
                                  "Expression": {
                                    "SourceRef": {
                                      "Entity": "Order Measures"
                                    }
                                  },
                                  "Property": "Diff Added vs Removed Dishes"
                                }
                              },
                              "Right": {
                                "Literal": {
                                  "Value": "0D"
                                }
                              }
                            }
                          },
                          "Value": {
                            "Literal": {
                              "Value": "'#C1DECB'"
                            }
                          }
                        }
                      ]
                    }
                  }
                }
              }
            }
          },
          "selector": {
            "data": [
              {
                "dataViewWildcard": {
                  "matchingOption": 1
                }
              }
            ]
          }
        }
      ]
    },
    "drillFilterOtherVisuals": true
  }
}