{
  "$schema": "https://developer.microsoft.com/json-schemas/fabric/item/report/definition/visualContainer/1.3.0/schema.json",
  "name": "49b8967e540ce6aa4beb",
  "position": {
    "x": 668.75,
    "y": 16.25,
    "z": 3000,
    "height": 320,
    "width": 555,
    "tabOrder": 3000
  },
  "visual": {
    "visualType": "clusteredColumnChart",
    "query": {
      "queryState": {
        "Category": {
          "projections": [
            {
              "field": {
                "Column": {
                  "Expression": {
                    "SourceRef": {
                      "Entity": "Companies"
                    }
                  },
                  "Property": "Company Name"
                }
              },
              "queryRef": "Companies.Company Name",
              "nativeQueryRef": "Company Name",
              "active": true
            }
          ]
        },
        "Series": {
          "projections": [
            {
              "field": {
                "Column": {
                  "Expression": {
                    "SourceRef": {
                      "Entity": "Origin of Preselected Dishes"
                    }
                  },
                  "Property": "Preselector Category"
                }
              },
              "queryRef": "Origin of Preselected Dishes.Preselector Category",
              "nativeQueryRef": "Preselector Category"
            }
          ]
        },
        "Y": {
          "projections": [
            {
              "field": {
                "Measure": {
                  "Expression": {
                    "SourceRef": {
                      "Entity": "Order Measures"
                    }
                  },
                  "Property": "Average Order Value Gross Ex Vat"
                }
              },
              "queryRef": "Order Measures.Average Order Value Gross Ex Vat",
              "nativeQueryRef": "Average Order Value Gross Ex Vat"
            }
          ]
        }
      },
      "sortDefinition": {
        "sort": [
          {
            "field": {
              "Column": {
                "Expression": {
                  "SourceRef": {
                    "Entity": "Companies"
                  }
                },
                "Property": "Company Name"
              }
            },
            "direction": "Ascending"
          }
        ]
      }
    },
    "objects": {
      "categoryAxis": [
        {
          "properties": {
            "fontSize": {
              "expr": {
                "Literal": {
                  "Value": "8D"
                }
              }
            },
            "maxMarginFactor": {
              "expr": {
                "Literal": {
                  "Value": "23L"
                }
              }
            },
            "showAxisTitle": {
              "expr": {
                "Literal": {
                  "Value": "false"
                }
              }
            }
          }
        }
      ],
      "valueAxis": [
        {
          "properties": {
            "showAxisTitle": {
              "expr": {
                "Literal": {
                  "Value": "false"
                }
              }
            }
          }
        }
      ]
    },
    "visualContainerObjects": {
      "title": [
        {
          "properties": {
            "show": {
              "expr": {
                "Literal": {
                  "Value": "true"
                }
              }
            },
            "text": {
              "expr": {
                "Literal": {
                  "Value": "'Average Order Value Gross ex Vat'"
                }
              }
            }
          }
        }
      ],
      "padding": [
        {
          "properties": {
            "top": {
              "expr": {
                "Literal": {
                  "Value": "10D"
                }
              }
            },
            "left": {
              "expr": {
                "Literal": {
                  "Value": "10D"
                }
              }
            },
            "bottom": {
              "expr": {
                "Literal": {
                  "Value": "10D"
                }
              }
            },
            "right": {
              "expr": {
                "Literal": {
                  "Value": "10D"
                }
              }
            }
          }
        }
      ],
      "spacing": [
        {
          "properties": {
            "verticalSpacing": {
              "expr": {
                "Literal": {
                  "Value": "10D"
                }
              }
            }
          }
        }
      ],
      "lockAspect": [
        {
          "properties": {
            "show": {
              "expr": {
                "Literal": {
                  "Value": "false"
                }
              }
            }
          }
        }
      ],
      "dropShadow": [
        {
          "properties": {
            "show": {
              "expr": {
                "Literal": {
                  "Value": "true"
                }
              }
            },
            "preset": {
              "expr": {
                "Literal": {
                  "Value": "'Custom'"
                }
              }
            },
            "transparency": {
              "expr": {
                "Literal": {
                  "Value": "80D"
                }
              }
            }
          }
        }
      ]
    },
    "drillFilterOtherVisuals": true
  },
  "filterConfig": {
    "filters": [
      {
        "name": "5614a845b2b300434a49",
        "ordinal": 0,
        "field": {
          "Measure": {
            "Expression": {
              "SourceRef": {
                "Entity": "Order Measures"
              }
            },
            "Property": "Average Number of Swaps per Order"
          }
        },
        "type": "Advanced",
        "howCreated": "User"
      },
      {
        "name": "af03ef0ce6768ebde0e7",
        "ordinal": 1,
        "field": {
          "Measure": {
            "Expression": {
              "SourceRef": {
                "Entity": "Order Measures"
              }
            },
            "Property": "Number of Orders"
          }
        },
        "type": "Advanced",
        "howCreated": "User"
      },
      {
        "name": "39009aceca00da6da115",
        "ordinal": 2,
        "field": {
          "Measure": {
            "Expression": {
              "SourceRef": {
                "Entity": "Order Measures"
              }
            },
            "Property": "Share of Swapped Dishes"
          }
        },
        "type": "Advanced",
        "howCreated": "User"
      },
      {
        "name": "b76f519eee2e7ced7231",
        "ordinal": 3,
        "field": {
          "Column": {
            "Expression": {
              "SourceRef": {
                "Entity": "Date"
              }
            },
            "Property": "Week"
          }
        },
        "type": "Advanced",
        "howCreated": "User"
      },
      {
        "name": "5a8db99210dd2dc64e03",
        "ordinal": 4,
        "field": {
          "Column": {
            "Expression": {
              "SourceRef": {
                "Entity": "Companies"
              }
            },
            "Property": "Company Name"
          }
        }
      },
      {
        "name": "d5e9f91a06b52dd18c2a",
        "ordinal": 5,
        "field": {
          "Measure": {
            "Expression": {
              "SourceRef": {
                "Entity": "Order Measures"
              }
            },
            "Property": "Average Order Value Gross Ex Vat"
          }
        },
        "type": "Advanced"
      },
      {
        "name": "b123309080c1046d205a",
        "ordinal": 6,
        "field": {
          "Column": {
            "Expression": {
              "SourceRef": {
                "Entity": "Billing Agreements"
              }
            },
            "Property": "OneSub Flag"
          }
        },
        "howCreated": "User"
      }
    ],
    "filterSortOrder": "Custom"
  }
}