{
  "$schema": "https://developer.microsoft.com/json-schemas/fabric/item/report/definition/visualContainer/2.1.0/schema.json",
  "name": "b3e40e547acbae4c25b4",
  "position": {
    "x": 32,
    "y": 400.00000000000006,
    "z": 6000,
    "height": 288,
    "width": 784,
    "tabOrder": 6000
  },
  "visual": {
    "visualType": "pivotTable",
    "query": {
      "queryState": {
        "Rows": {
          "projections": [
            {
              "field": {
                "Column": {
                  "Expression": {
                    "SourceRef": {
                      "Entity": "Brands"
                    }
                  },
                  "Property": "Brand"
                }
              },
              "queryRef": "Brands.Brand",
              "nativeQueryRef": "Brand",
              "active": true
            },
            {
              "field": {
                "HierarchyLevel": {
                  "Expression": {
                    "Hierarchy": {
                      "Expression": {
                        "SourceRef": {
                          "Entity": "Dates"
                        }
                      },
                      "Hierarchy": "Financial Date Hierarchy"
                    }
                  },
                  "Level": "Year"
                }
              },
              "queryRef": "Dates.Financial Date Hierarchy.Year",
              "nativeQueryRef": "Financial Date Hierarchy Year",
              "active": false
            },
            {
              "field": {
                "HierarchyLevel": {
                  "Expression": {
                    "Hierarchy": {
                      "Expression": {
                        "SourceRef": {
                          "Entity": "Dates"
                        }
                      },
                      "Hierarchy": "Financial Date Hierarchy"
                    }
                  },
                  "Level": "Quarter"
                }
              },
              "queryRef": "Dates.Financial Date Hierarchy.Quarter",
              "nativeQueryRef": "Financial Date Hierarchy Quarter",
              "active": false
            },
            {
              "field": {
                "HierarchyLevel": {
                  "Expression": {
                    "Hierarchy": {
                      "Expression": {
                        "SourceRef": {
                          "Entity": "Dates"
                        }
                      },
                      "Hierarchy": "Financial Date Hierarchy"
                    }
                  },
                  "Level": "Month"
                }
              },
              "queryRef": "Dates.Financial Date Hierarchy.Month",
              "nativeQueryRef": "Financial Date Hierarchy Month",
              "active": false
            },
            {
              "field": {
                "HierarchyLevel": {
                  "Expression": {
                    "Hierarchy": {
                      "Expression": {
                        "SourceRef": {
                          "Entity": "Dates"
                        }
                      },
                      "Hierarchy": "Financial Date Hierarchy"
                    }
                  },
                  "Level": "Week"
                }
              },
              "queryRef": "Dates.Financial Date Hierarchy.Week",
              "nativeQueryRef": "Financial Date Hierarchy Week",
              "active": false
            }
          ]
        },
        "Values": {
          "projections": [
            {
              "field": {
                "Measure": {
                  "Expression": {
                    "SourceRef": {
                      "Entity": "Order Measures"
                    }
                  },
                  "Property": "Number of Orders"
                }
              },
              "queryRef": "Order Measures.Number of Orders",
              "nativeQueryRef": "Number of Orders"
            },
            {
              "field": {
                "Measure": {
                  "Expression": {
                    "SourceRef": {
                      "Entity": "Order Measures"
                    }
                  },
                  "Property": "Number of Ordered Units"
                }
              },
              "queryRef": "Order Measures.Number of Ordered Units",
              "nativeQueryRef": "Number of Ordered Units"
            },
            {
              "field": {
                "Measure": {
                  "Expression": {
                    "SourceRef": {
                      "Entity": "Order Measures"
                    }
                  },
                  "Property": "ATV Net Ex Vat"
                }
              },
              "queryRef": "Order Measures.ATV Net Ex Vat",
              "nativeQueryRef": "ATV Net Ex Vat"
            },
            {
              "field": {
                "Measure": {
                  "Expression": {
                    "SourceRef": {
                      "Entity": "Order Measures"
                    }
                  },
                  "Property": "Order Value Gross Ex Vat"
                }
              },
              "queryRef": "Order Measures.Order Value Gross Ex Vat",
              "nativeQueryRef": "Order Value Gross Ex Vat"
            }
          ]
        }
      }
    },
    "expansionStates": [
      {
        "roles": [
          "Rows"
        ],
        "levels": [
          {
            "queryRefs": [
              "Brands.Brand"
            ],
            "isCollapsed": true,
            "isPinned": true
          },
          {
            "queryRefs": [
              "Dates.Financial Date Hierarchy.Year"
            ],
            "isCollapsed": true,
            "identityKeys": [
              {
                "Column": {
                  "Expression": {
                    "SourceRef": {
                      "Entity": "Dates"
                    }
                  },
                  "Property": "Financial Year"
                }
              }
            ],
            "isPinned": true
          },
          {
            "queryRefs": [
              "Dates.Financial Date Hierarchy.Quarter"
            ],
            "isCollapsed": true,
            "identityKeys": [
              {
                "Column": {
                  "Expression": {
                    "SourceRef": {
                      "Entity": "Dates"
                    }
                  },
                  "Property": "Financial Quarter"
                }
              }
            ],
            "isPinned": true
          },
          {
            "queryRefs": [
              "Dates.Financial Date Hierarchy.Month"
            ],
            "isCollapsed": true,
            "identityKeys": [
              {
                "Column": {
                  "Expression": {
                    "SourceRef": {
                      "Entity": "Dates"
                    }
                  },
                  "Property": "Financial Month Name"
                }
              }
            ],
            "isPinned": true
          },
          {
            "queryRefs": [
              "Dates.Financial Date Hierarchy.Week"
            ],
            "isCollapsed": true,
            "isPinned": true
          }
        ],
        "root": {}
      }
    ],
    "objects": {
      "columnHeaders": [
        {
          "properties": {
            "wordWrap": {
              "expr": {
                "Literal": {
                  "Value": "true"
                }
              }
            },
            "autoSizeColumnWidth": {
              "expr": {
                "Literal": {
                  "Value": "true"
                }
              }
            }
          }
        }
      ],
      "columnWidth": [
        {
          "properties": {},
          "selector": {
            "metadata": "Order Measures.Number of Orders"
          }
        },
        {
          "properties": {},
          "selector": {
            "metadata": "Order Measures.Number of Ordered Units"
          }
        },
        {
          "properties": {},
          "selector": {
            "metadata": "Order Measures.ATV Net Ex Vat"
          }
        },
        {
          "properties": {},
          "selector": {
            "metadata": "Order Measures.Order Value Gross Ex Vat"
          }
        }
      ]
    },
    "drillFilterOtherVisuals": true
  }
}